[
  {
    "endTime" : "2022-11-15 14:24",
    "artistName" : "Ed Sheeran",
    "trackName" : "Bad Habits",
    "msPlayed" : 8060
  },
  {
    "endTime" : "2022-11-16 16:42",
    "artistName" : "Alok",
    "trackName" : "Un Ratito",
    "msPlayed" : 1680
  },
  {
    "endTime" : "2022-11-16 16:47",
    "artistName" : "Kaushik-Guddu",
    "trackName" : "Dil (From \"Ek Villain Returns\")",
    "msPlayed" : 309149
  },
  {
    "endTime" : "2022-11-16 16:47",
    "artistName" : "Kaushik-Guddu",
    "trackName" : "Teri Ada",
    "msPlayed" : 4040
  },
  {
    "endTime" : "2022-11-17 17:39",
    "artistName" : "Jubin Nautiyal",
    "trackName" : "Barsaat Ho Jaaye",
    "msPlayed" : 102465
  },
  {
    "endTime" : "2022-11-17 17:40",
    "artistName" : "SS Animations",
    "trackName" : "Hai Katha Sangram Ki",
    "msPlayed" : 11760
  },
  {
    "endTime" : "2022-11-17 17:40",
    "artistName" : "Sharmin Anand",
    "trackName" : "Yada Yada Hi Dharmasya",
    "msPlayed" : 22917
  },
  {
    "endTime" : "2022-11-17 17:41",
    "artistName" : "Hemant Shreyash",
    "trackName" : "Draupadi",
    "msPlayed" : 16544
  },
  {
    "endTime" : "2022-11-17 17:41",
    "artistName" : "Trisha Parui",
    "trackName" : "Madhurashtakam",
    "msPlayed" : 6562
  },
  {
    "endTime" : "2022-11-17 17:41",
    "artistName" : "Paras Nath",
    "trackName" : "Krishna Theme (Flute)",
    "msPlayed" : 16436
  },
  {
    "endTime" : "2022-11-17 17:41",
    "artistName" : "Lakhinandan Lahon",
    "trackName" : "Krishna Krish Flute",
    "msPlayed" : 7170
  },
  {
    "endTime" : "2022-11-17 17:42",
    "artistName" : "Hemant Shreyash",
    "trackName" : "Karna",
    "msPlayed" : 47572
  },
  {
    "endTime" : "2022-11-17 17:42",
    "artistName" : "Hemant Shreyash",
    "trackName" : "Mahabharat Main Theme",
    "msPlayed" : 20250
  },
  {
    "endTime" : "2022-11-17 17:43",
    "artistName" : "Hemant Shreyash",
    "trackName" : "Karna",
    "msPlayed" : 1439
  },
  {
    "endTime" : "2022-11-17 17:43",
    "artistName" : "Lakhinandan Lahon",
    "trackName" : "Krishna Krish Flute",
    "msPlayed" : 4811
  },
  {
    "endTime" : "2022-11-17 17:44",
    "artistName" : "oldhouseproduction",
    "trackName" : "Mahabharat Title Track",
    "msPlayed" : 65230
  },
  {
    "endTime" : "2022-11-17 17:44",
    "artistName" : "Hemant Shreyash",
    "trackName" : "Karna",
    "msPlayed" : 38395
  },
  {
    "endTime" : "2022-11-17 17:47",
    "artistName" : "oldhouseproduction",
    "trackName" : "Mahabharat Title Track",
    "msPlayed" : 34838
  },
  {
    "endTime" : "2022-11-18 16:01",
    "artistName" : "Ankit Tiwari",
    "trackName" : "Galliyan Returns (From \"Ek Villain Returns\")",
    "msPlayed" : 219080
  },
  {
    "endTime" : "2022-11-18 16:02",
    "artistName" : "Puneet Dixit",
    "trackName" : "Lakeerien 2.0 (From \"Guddan Tumse Na Ho Paayega\")",
    "msPlayed" : 7794
  },
  {
    "endTime" : "2022-11-18 16:02",
    "artistName" : "Jubin Nautiyal",
    "trackName" : "Pyaar Tune Kya Kiya",
    "msPlayed" : 9225
  },
  {
    "endTime" : "2022-11-18 16:02",
    "artistName" : "Goldsmth",
    "trackName" : "Qismat Ka Khel",
    "msPlayed" : 34240
  },
  {
    "endTime" : "2022-11-18 16:02",
    "artistName" : "Sachet Tandon",
    "trackName" : "Sachiya Mohabbatan (From \"Arjun Patiala\")",
    "msPlayed" : 13584
  },
  {
    "endTime" : "2022-11-18 16:03",
    "artistName" : "Gurnam Bhullar",
    "trackName" : "Ruttan",
    "msPlayed" : 58424
  },
  {
    "endTime" : "2022-11-18 16:03",
    "artistName" : "Gurnam Bhullar",
    "trackName" : "Udaariyaan",
    "msPlayed" : 10029
  },
  {
    "endTime" : "2023-05-23 13:04",
    "artistName" : "Aniket Desai",
    "trackName" : "Kho Jayenge",
    "msPlayed" : 23854
  }
]